llama_index/postprocessor/colbert_rerank/__init__.py
llama_index/postprocessor/colbert_rerank/base.py
llama_index_postprocessor_colbert_rerank-0.4.1.dist-info/METADATA
llama_index_postprocessor_colbert_rerank-0.4.1.dist-info/WHEEL
llama_index_postprocessor_colbert_rerank-0.4.1.dist-info/licenses/LICENSE
llama_index_postprocessor_colbert_rerank-0.4.1.dist-info/RECORD
